commitfmt_linux/__init__.py
commitfmt_linux-1.0.4.dist-info/METADATA
commitfmt_linux-1.0.4.dist-info/WHEEL
commitfmt_linux-1.0.4.dist-info/top_level.txt
commitfmt_linux-1.0.4.dist-info/RECORD
